lib/__init__.py
lib/api.py
lib/database.py
lib/models.py
lib/settings.py
lib/config/__init__.py
lib/config/categories.json
lib/config/categories.schema.json
lib/config/commands.json
lib/config/commands.schema.json
lib/config/loader.py
lib/config/project-types.json
lib/config/project-types.schema.json
lib/config/secrets.json
lib/config/secrets.schema.json
lib/config/tags.json
lib/config/tags.schema.json
server/__init__.py
server/bridge.py
server/cli.py
server/context.py
server/server.py
mem_box-0.1.1.dist-info/METADATA
mem_box-0.1.1.dist-info/WHEEL
mem_box-0.1.1.dist-info/entry_points.txt
mem_box-0.1.1.dist-info/licenses/LICENSE
mem_box-0.1.1.dist-info/RECORD
