Metadata-Version: 2.4
Name: mem-box
Version: 0.1.1
Summary: A personal knowledge base for commands and workflows, accessible via MCP
License: MIT
License-File: LICENSE
Requires-Python: >=3.10
Requires-Dist: fastmcp>=0.2.0
Requires-Dist: neo4j>=5.14.0
Requires-Dist: pydantic-settings>=2.1.0
Requires-Dist: pydantic>=2.5.0
Requires-Dist: python-dotenv>=1.0.0
Requires-Dist: rapidfuzz>=3.0.0
Requires-Dist: rich>=13.7.0
Requires-Dist: typer>=0.9.0
Provides-Extra: dev
Requires-Dist: mypy>=1.8.0; extra == 'dev'
Requires-Dist: pre-commit>=3.6.0; extra == 'dev'
Requires-Dist: pytest-asyncio>=0.23.0; extra == 'dev'
Requires-Dist: pytest-cov>=4.1.0; extra == 'dev'
Requires-Dist: pytest>=8.0.0; extra == 'dev'
Requires-Dist: ruff>=0.1.8; extra == 'dev'
Requires-Dist: testcontainers[neo4j]>=4.0.0; extra == 'dev'
